hoodini_colab/__init__.py
hoodini_colab/utils.py
hoodini_colab/widget.py
hoodini_colab/widget.js
hoodini_colab-0.1.5.dist-info/METADATA
hoodini_colab-0.1.5.dist-info/WHEEL
hoodini_colab-0.1.5.dist-info/licenses/LICENSE
hoodini_colab-0.1.5.dist-info/RECORD
