Metadata-Version: 2.4
Name: hoodini-colab
Version: 0.1.5
Summary: Interactive parameter configurator for the Hoodini CLI genomic neighborhood analysis tool
Project-URL: Homepage, https://hoodini.bio
Project-URL: Documentation, https://github.com/pentamorfico/hoodini-colab
Project-URL: Repository, https://github.com/pentamorfico/hoodini-colab
Author: Hoodini Team
License: MIT
License-File: LICENSE
Keywords: bioinformatics,genomics,hoodini,jupyter,widget
Classifier: Development Status :: 4 - Beta
Classifier: Framework :: Jupyter
Classifier: Intended Audience :: Science/Research
Classifier: License :: OSI Approved :: MIT License
Classifier: Programming Language :: Python :: 3
Classifier: Programming Language :: Python :: 3.9
Classifier: Programming Language :: Python :: 3.10
Classifier: Programming Language :: Python :: 3.11
Classifier: Programming Language :: Python :: 3.12
Classifier: Topic :: Scientific/Engineering :: Bio-Informatics
Requires-Python: >=3.9
Requires-Dist: anywidget>=0.9.0
Requires-Dist: ipython>=7.0.0
Requires-Dist: traitlets>=5.0.0
Provides-Extra: dev
Requires-Dist: ipykernel>=6.29.0; extra == 'dev'
Requires-Dist: mypy>=1.11.0; extra == 'dev'
Requires-Dist: pdoc>=14.0.0; extra == 'dev'
Requires-Dist: pydoc-markdown>=4.8.2; extra == 'dev'
Requires-Dist: pytest-cov>=5.0.0; extra == 'dev'
Requires-Dist: pytest>=8.0.0; extra == 'dev'
Requires-Dist: ruff>=0.6.0; extra == 'dev'
